{
    "accounts": [
    {
        "env": "Connect-Dev",
        "branch": "develop",
        "enabled": true,
        "account": "381492049335",
        "region": ["us-east-1"],
        "app": "ACME"
    },
    {
        "env": "Connect-Stage",
        "branch": "staging",
        "enabled": true,
        "account": "533267161761",
        "region": ["us-east-1"],
        "app": "ACME"
    },
    {
        "env": "Connect-Prod",
        "branch": "main",
        "enabled": true,
        "account": "730335194307",
        "region": ["us-east-1"],
        "app": "ACME"
    }]
}
